{
    "website": "https://backdropcms.org",
    "implies": "PHP",
    "excludes": "Drupal",
    "matches": [
        {
            "regexp": ".*",
            "search": "headers[x-backdrop-cache]"
        },
        {
            "offset": 1,
            "regexp": "^Backdrop CMS(?:\\s([\\d.]+))?",
            "search": "headers[x-generator]"
        },
        {
            "offset": 1,
            "regexp": "^Backdrop CMS(?:\\s([\\d.]+))?",
            "search": "meta[generator]"
        }
    ],
    "name": "Backdrop"
}