{
    "matches": [
        {
            "regexp": "FlexCMP.+\\[v\\. ([\\d.]+)",
            "search": "headers[x-powered-by]",
            "offset": 1
        },
        {
            "regexp": ".*",
            "search": "headers[x-flex-lang]"
        },
        {
            "offset": 1,
            "regexp": "<!--[^>]+FlexCMP[^>v]+v\\. ([\\d.]+)"
        },
        {
            "regexp": "^FlexCMP",
            "search": "meta[generator]"
        }
    ],
    "website": "http://www.flexcmp.com/cms/home",
    "name": "FlexCMP"
}