{
    "matches": [
        {
            "regexp": ".*",
            "search": "meta[foswiki.SERVERTIME]"
        },
        {
            "regexp": ".*",
            "search": "meta[foswiki.WIKINAME]"
        },
        {
            "regexp": "<div class=\"foswiki(?:Copyright|Page|Main)\">"
        },
        {
            "regexp": ".*",
            "search": "headers[x-foswikiuri]"
        },
        {
            "regexp": ".*",
            "search": "headers[x-foswikiaction]"
        },
        {
            "regexp": ".*",
            "search": "cookies[FOSWIKISTRIKEONE]"
        },
        {
            "regexp": ".*",
            "search": "cookies[SFOSWIKISID]"
        }
    ],
    "website": "http://foswiki.org",
    "name": "Foswiki",
    "implies": "Perl"
}