{
    "website": "https://www.optimizely.com/",
    "name": "Optimizely CMS",
    "matches": [
        {
            "search": "cookies[EPiTrace]",
            "regexp": ".*"
        },
        {
            "search": "cookies[EPiSessionId]",
            "regexp": ".*"
        },
        {
            "search": "cookies[EPiServer]",
            "regexp": ".*"
        },
        {
            "search": "meta[generator]",
            "regexp": "EPiServer"
        }
    ],
    "implies": "Microsoft ASP.NET"
}