{
    "matches": [
        {
            "search": "cookies[spp_orderform]",
            "regexp": ".*"
        },
        {
            "search": "cookies[spp_csrf]",
            "certainty": 25,
            "regexp": ".*"
        },
        {
            "search": "cookies[spp_session]",
            "certainty": 25,
            "regexp": ".*"
        },
        {
            "search": "meta[server]",
            "regexp": "app.spp.co"
        }
    ],
    "name": "Service Provider Pro",
    "website": "https://spp.co"
}