{
    "name": "TiddlyWiki",
    "matches": [
        {
            "regexp": "^TiddlyWiki created by Jeremy Ruston",
            "search": "meta[copyright]"
        },
        {
            "regexp": "^TiddlyWiki$",
            "search": "meta[application-name]"
        },
        {
            "offset": 1,
            "regexp": "^(.+)$",
            "search": "meta[tiddlywiki-version]"
        },
        {
            "regexp": "^TiddlyWiki$",
            "search": "meta[generator]"
        },
        {
            "regexp": "<[^>]*type=[^>]text\\/vnd\\.tiddlywiki"
        }
    ],
    "website": "http://tiddlywiki.com"
}